LICENSE
MANIFEST.in
README.rst
setup.py
aino_mutations.egg-info/PKG-INFO
aino_mutations.egg-info/SOURCES.txt
aino_mutations.egg-info/dependency_links.txt
aino_mutations.egg-info/not-zip-safe
aino_mutations.egg-info/top_level.txt
mutations/__init__.py
mutations/evolution.py
mutations/models.py
mutations/conf/__init__.py
mutations/conf/defaults.py
mutations/management/__init__.py
mutations/management/commands/__init__.py
mutations/management/commands/mutate.py
mutations/management/commands/runmutation.py