Metadata-Version: 1.0
Name: aino-mutations
Version: 0.1.0.0
Summary: Mutating for evolution using Django and Mercurial
Home-page: http://bitbucket.org/aino/aino-mutations/
Author: Mikko Hellsing
Author-email: mikko@aino.se
License: BSD
Platform: any
Classifier: Development Status :: 3 - Alpha
Classifier: Environment :: Web Environment
Classifier: Intended Audience :: Developers
Classifier: License :: OSI Approved :: BSD License
Classifier: Operating System :: OS Independent
Classifier: Programming Language :: Python
Classifier: Topic :: Database
Classifier: Topic :: Software Development :: Version Control
Classifier: Framework :: Django
